pinspector/__init__.py
pinspector/invoker.py
pinspector/server.py
pinspector/static/pin/index.html
pinspector/static/pin/invoker.js
pinspector/static/pin/pin.html
pinspector-1.0.dist-info/LICENSE
pinspector-1.0.dist-info/METADATA
pinspector-1.0.dist-info/WHEEL
pinspector-1.0.dist-info/top_level.txt
pinspector-1.0.dist-info/RECORD
