Metadata-Version: 2.1
Name: pinspector
Version: 1.0
Summary: Live object inspector
Home-page: https://github.com/ilndinesh/pinspector
Author: Dinesh Ilindra
Author-email: dinesh.iln@gmail.com
License: UNKNOWN
Platform: UNKNOWN
Classifier: Programming Language :: Python :: 3
Classifier: License :: OSI Approved :: MIT License
Classifier: Operating System :: OS Independent
Requires-Python: >=3.6
